{
	[
		{"elementos":[12,8,24,6,10],
		"pistas_elementos_index":[3],
		"factor":2,
		"respuestas_index":[1],
		"respuestas":[16]},

		{"elementos":[12,8,24,6,10],
		"pistas_elementos_index":[4],
		"factor":0.5,
		"respuestas_index":[0],
		"respuestas":[1]},

		{"elementos":[12,8,24,6,10],
		"pistas_elementos_index":[4],
		"factor":2,
		"respuestas_index":[2],
		"respuestas":[48]},

		{"elementos":[12,8,24,6,10],
		"pistas_elementos_index":[4],
		"factor":0.5,
		"respuestas_index":[2],
		"respuestas":[12]},

		{"elementos":[12,8,24,6,10],
		"pistas_elementos_index":[2],
		"factor":0.5,
		"respuestas_index":[3],
		"respuestas":[3]},

		{"elementos":[12,8,24,6,10],
		"pistas_elementos_index":[1],
		"factor":2,
		"respuestas_index":[2],
		"respuestas":[48]},

		{"elementos":[12,8,24,6,10],
		"pistas_elementos_index":[0],
		"factor":0.5,
		"respuestas_index":[3],
		"respuestas":[3]},

		{"elementos":[12,8,24,6,10],
		"pistas_elementos_index":[0],
		"factor":2,
		"respuestas_index":[2],
		"respuestas":[48]},

		{"elementos":[12,8,24,6,10],
		"pistas_elementos_index":[3],
		"factor":0.5,
		"respuestas_index":[4],
		"respuestas":[5]}
		]
}
